Metadata-Version: 2.1
Name: inoryp
Version: 2.0.20
Summary: Essa biblioteca foi desenvolvida com o intuito de fornecer o acesso rápido ao seu Endereço IP(LAN).
Home-page: https://github.com/R0htg0r
Author: R0htg0r
Author-email: osvaldo.pedreiro.ecaminhoneiro@gmail.com
License: MIT
Keywords: Python,Python3,IP,API,Informations,InformaIPSecurity,Requests
Platform: UNKNOWN
Classifier: License :: OSI Approved :: MIT License
Classifier: Programming Language :: Python :: 3.6
Classifier: Programming Language :: Python :: 3.7
Classifier: Programming Language :: Python :: 3.8
